cdk_events_notify/__init__.py
cdk_events_notify/py.typed
cdk_events_notify/_jsii/__init__.py
cdk_events_notify/_jsii/cdk-events-notify@2.2.717.jsii.tgz
cdk_events_notify-2.2.717.dist-info/LICENSE
cdk_events_notify-2.2.717.dist-info/METADATA
cdk_events_notify-2.2.717.dist-info/WHEEL
cdk_events_notify-2.2.717.dist-info/top_level.txt
cdk_events_notify-2.2.717.dist-info/RECORD
